{
  "id": "69c2f6e4a1a5777ea48f85b1",
  "slug": "bursaspor'dan-sampiyonluk-yarisinda-kritik-galibiyet-264508",
  "title": "Bursaspor'dan şampiyonluk yarışında kritik galibiyet",
  "summary": "Bursaspor, TFF 2. Lig Kırmızı Grup 29. hafta karşılaşmasında Gebzespor'u 2-0 mağlup ederek önemli bir galibiyet aldı. Maçta 41 bin 870 taraftar bulundu. İlk yarıda gol çıkmadı, ancak Bursaspor ikinci yarıda 70. dakikada İlhan Depe ve 75. dakikada Baran Başyiğit'in golleriyle galibiyeti elde etti. Böylece Bursaspor, puanını 67'ye yükseltti.",
  "content": "Bursaspor, Gebzespor karşısında ikinci yarıda bulduğu gollerle şampiyonluk yarışında önemli bir galibiyet alırken, müsabakayı 41 bin 870 taraftar izledi. TFF 2. Lig Kırmızı Grup 29. hafta karşılaşmasında Bursaspor, sahasında Güzide Gebzespor'u 2-0 mağlup ederek kritik bir galibiyet aldı. Atatürk Spor Kompleksi Matlı Stadyumu'nda oynanan mücadelede yeşil-beyazlı ekip, ikinci yarıda bulduğu gollerle sonuca gitti. Bursaspor'un bu hafta oynadığı karşılaşmayı 41 bin 870 taraftarın tribünden takip etti.\n\n**İlk yarıda gol sesi çıkmadı**  \nKarşılaşmanın ilk 45 dakikasında Bursaspor önemli fırsatlar yakalasa da golü bulamadı. Batuhan Yayıkçı'nın kafa vuruşunda topun çizgiden çıkarılması ve Salih Kavrazlı'nın kaçırdığı net pozisyon ilk yarının öne çıkan anları oldu. Konuk ekip Güzide Gebzespor ise savunma ağırlıklı bir oyun sergileyerek ilk yarıyı golsüz eşitlikle tamamladı.\n\n**Galibiyet 2. yarıda geldi**  \nİkinci yarıya daha istekli başlayan Bursaspor, aradığı golü 70. dakikada buldu. Sol kanattan yapılan ortada oluşan karambolde İlhan Depe topu ağlara göndererek takımını öne geçirdi. Bu golden sadece 5 dakika sonra fark ikiye çıktı. Hızlı gelişen atakta İlhan Depe'nin yerden ortasında Baran Başyiğit şık bir vuruşla skoru 2-0'a taşıdı. Kalan dakikalarda oyunun kontrolünü elinde tutan Bursaspor, rakibine net fırsat vermedi ve mücadeleyi 2-0 kazanarak sahadan 3 puanla ayrıldı. Yeşil-beyazlılar bu sonuçla zirvede puanını 67'ye yükseltti.  \n\n- BURSA  \nKaynak: İhlas Haber Ajansı",
  "imageUrl": "https://foto.haberler.com/haber/2026/03/24/bursaspor-dan-sampiyonluk-yarisinda-kritik-19686042_amp.jpg",
  "source": "Haberler.com",
  "category": "Gündem",
  "publishedAt": "2026-03-24T20:41:08.473Z",
  "url": "https://pusholder.app/haber/bursaspor'dan-sampiyonluk-yarisinda-kritik-galibiyet-264508",
  "score": 70,
  "scoreBreakdown": {
    "base": 40,
    "source": 5,
    "breakingNews": 0,
    "vipPerson": 0,
    "category": 10,
    "highImpact": 10,
    "specialDay": 0,
    "viral": 0,
    "hasImage": 5,
    "clickbait": 0,
    "lowValue": 0,
    "similarity": 0,
    "darkNewsPenalty": 0
  },
  "tier": "site",
  "similarity": 0,
  "isDarkNews": false,
  "vipMention": []
}